django_db_lock/__init__.py
django_db_lock/admin.py
django_db_lock/apps.py
django_db_lock/client.py
django_db_lock/models.py
django_db_lock/server.py
django_db_lock/settings.py
django_db_lock/urls.py
django_db_lock/locale/zh_Hans/LC_MESSAGES/django.mo
django_db_lock/locale/zh_Hans/LC_MESSAGES/django.po
django_db_lock/migrations/0001_initial.py
django_db_lock/migrations/0002_auto_20210409_1440.py
django_db_lock/migrations/__init__.py
django_db_lock-0.6.3.dist-info/LICENSE
django_db_lock-0.6.3.dist-info/METADATA
django_db_lock-0.6.3.dist-info/WHEEL
django_db_lock-0.6.3.dist-info/top_level.txt
django_db_lock-0.6.3.dist-info/RECORD
