Metadata-Version: 2.1
Name: django-db-lock
Version: 0.6.3
Summary: Lock something and keep status in database. A simple distributed lock system.
Author: Chao WeiZhi
Author-email: chaoweizhi@zencore.cn
Maintainer: Chao WeiZhi
Maintainer-email: chaoweizhi@zencore.cn
License: MIT
Keywords: django extentions,django db lock
Classifier: Development Status :: 5 - Production/Stable
Classifier: Intended Audience :: Developers
Classifier: Topic :: Software Development :: Libraries :: Python Modules
Classifier: License :: OSI Approved :: MIT License
Classifier: Programming Language :: Python :: 3
Classifier: Programming Language :: Python :: 3 :: Only
License-File: LICENSE
Requires-Dist: django >=2.2.20
Requires-Dist: django-redis >=4.12.1
Requires-Dist: django-apiview >=0.9.27
Requires-Dist: requests >=2.25.1
